rest_framework_simplejwt/__init__.py
rest_framework_simplejwt/authentication.py
rest_framework_simplejwt/backends.py
rest_framework_simplejwt/compat.py
rest_framework_simplejwt/exceptions.py
rest_framework_simplejwt/models.py
rest_framework_simplejwt/serializers.py
rest_framework_simplejwt/settings.py
rest_framework_simplejwt/state.py
rest_framework_simplejwt/tokens.py
rest_framework_simplejwt/utils.py
rest_framework_simplejwt/views.py
rest_framework_simplejwt/token_blacklist/__init__.py
rest_framework_simplejwt/token_blacklist/admin.py
rest_framework_simplejwt/token_blacklist/apps.py
rest_framework_simplejwt/token_blacklist/models.py
rest_framework_simplejwt/token_blacklist/management/__init__.py
rest_framework_simplejwt/token_blacklist/management/commands/__init__.py
rest_framework_simplejwt/token_blacklist/management/commands/flushexpiredtokens.py
rest_framework_simplejwt/token_blacklist/migrations/0001_initial.py
rest_framework_simplejwt/token_blacklist/migrations/0002_outstandingtoken_jti_hex.py
rest_framework_simplejwt/token_blacklist/migrations/0003_auto_20171017_2007.py
rest_framework_simplejwt/token_blacklist/migrations/0004_auto_20171017_2013.py
rest_framework_simplejwt/token_blacklist/migrations/0005_remove_outstandingtoken_jti.py
rest_framework_simplejwt/token_blacklist/migrations/0006_auto_20171017_2113.py
rest_framework_simplejwt/token_blacklist/migrations/0007_auto_20171017_2214.py
rest_framework_simplejwt/token_blacklist/migrations/0008_migrate_to_bigautofield.py
rest_framework_simplejwt/token_blacklist/migrations/0010_fix_migrate_to_bigautofield.py
rest_framework_simplejwt/token_blacklist/migrations/0011_linearizes_history.py
rest_framework_simplejwt/token_blacklist/migrations/0012_alter_outstandingtoken_user.py
rest_framework_simplejwt/token_blacklist/migrations/__init__.py
drfsimple2-0.0.5.dist-info/LICENSE
drfsimple2-0.0.5.dist-info/METADATA
drfsimple2-0.0.5.dist-info/WHEEL
drfsimple2-0.0.5.dist-info/top_level.txt
drfsimple2-0.0.5.dist-info/RECORD
